{"name":"Null-Sec Scr!pts","tagline":"","body":"## Welcome to Null-Sec's GitHub Page.\r\n\r\nThis is a pages for all of Null-Sec's projects and Scripts. \r\n\r\n\r\n\r\n### Installing\r\nOpen terminal and make sub-directory for your git clones\r\n```\r\nmkdir NSTools\r\ncd NSTools\r\ngit clone https://github.com/Null-Sec/NSTools.git\r\n```\r\n     \r\n     \r\n     \r\n### Running Scr!pts\r\nOpen terminal and go to the scr!pts directory\r\n```\r\ncd NSTools/Scr!pts/\r\n./{Scr!pt}\r\n```\r\nExample;\r\n```\r\n./WPA-BF.py \r\n```\r\n     \r\n     \r\n     \r\n### Tools\r\n* Null-Crypter (For Metasploit-Framework)\r\n     \r\n     \r\n     \r\n### Scr!pts\r\n* SSH Exploitation\r\n* WIDS \r\n* WPA-BF \r\n     \r\n     \r\n     \r\n### Authors and Contributors\r\nNull-Sec and The Null-Sec community http://www.null-sec.ru \r\n     \r\n     \r\n     \r\n### Support or Contact\r\nDuggan@Null-Sec.ru","google":"","note":"Don't delete this file! It's used internally to help with page regeneration."}